{"width":1024,"imagePath":"NewProject_1_tex.png","SubTexture":[{"frameWidth":1024,"y":559,"frameX":-535,"frameHeight":1024,"frameY":-804,"width":146,"height":160,"name":"Rogue_leg_r_01","x":870},{"frameWidth":1024,"y":849,"frameX":-579,"frameHeight":1024,"frameY":-922,"width":111,"height":76,"name":"Rogue_boot_r_01","x":1},{"frameWidth":1024,"y":397,"frameX":-298,"frameHeight":1024,"frameY":-804,"width":147,"height":160,"name":"Rogue_leg_l_01","x":870},{"width":102,"y":849,"height":66,"name":"Rogue_boot_l_01","x":114},{"frameWidth":1024,"y":436,"frameX":-677,"frameHeight":1024,"frameY":-794,"width":91,"height":94,"name":"Rogue_wrist_r_01","x":397},{"frameWidth":1024,"y":671,"frameX":-653,"frameHeight":1024,"frameY":-704,"width":93,"height":149,"name":"Rogue_elbow_r_01","x":485},{"frameWidth":1024,"y":1,"frameX":-594,"frameHeight":1024,"frameY":-546,"width":141,"height":196,"name":"Rogue_shoulder_r_01","x":869},{"frameWidth":1024,"y":436,"frameX":-294,"frameHeight":1024,"frameY":-722,"width":394,"height":211,"name":"Rogue_pelvis_01","x":1},{"frameWidth":1024,"y":371,"frameX":-304,"frameHeight":1024,"frameY":-530,"width":377,"height":298,"name":"Rogue_torso_01","x":491},{"frameWidth":1024,"y":779,"frameX":-209,"frameHeight":1024,"frameY":-806,"width":106,"height":93,"name":"Rogue_wrist_l_01","x":365},{"frameWidth":1024,"y":649,"frameX":-233,"frameHeight":1024,"frameY":-701,"width":118,"height":128,"name":"Rogue_elbow_l_01","x":365},{"frameWidth":1024,"y":199,"frameX":-260,"frameHeight":1024,"frameY":-546,"width":140,"height":196,"name":"Rogue_shoulder_l_01","x":870},{"frameWidth":1024,"y":1,"frameX":-316,"frameHeight":1024,"frameY":-253,"width":376,"height":368,"name":"Rogue_head_01","x":491},{"frameWidth":1024,"y":649,"frameX":-325,"frameHeight":1024,"frameY":-426,"width":362,"height":198,"name":"Rogue_face_01","x":1},{"frameWidth":1024,"y":1,"frameX":-246,"frameHeight":1024,"frameY":-187,"width":488,"height":433,"name":"Rogue_hood_01","x":1}],"height":1024,"name":"NewProject_1"}